log4p/__init__.py
log4p/log4p.json
log4p-2019.7.13.3.dist-info/LICENSE
log4p-2019.7.13.3.dist-info/METADATA
log4p-2019.7.13.3.dist-info/WHEEL
log4p-2019.7.13.3.dist-info/top_level.txt
log4p-2019.7.13.3.dist-info/RECORD
