Metadata-Version: 2.1
Name: log4p
Version: 2019.7.13.3
Summary: A simple log module based logging for python.
Home-page: https://github.com/talenhao/log4p
Author: Tianfei Hao(郝天飞)
Author-email: talenhao@gmail.com
License: BSD License
Keywords: logging,debug,log4p,log4python
Platform: UNKNOWN
Classifier: Development Status :: 5 - Production/Stable
Classifier: Intended Audience :: Developers
Classifier: Topic :: Software Development :: Build Tools
Classifier: License :: OSI Approved :: BSD License
Classifier: Programming Language :: Python :: 2
Classifier: Programming Language :: Python :: 3
Provides-Extra: test
Provides-Extra: dev
